beamnggym/__init__.py
beamnggym/version.txt
beamnggym/envs/__init__.py
beamnggym/envs/wcarace.py
BeamNG.gym-0.2.dist-info/AUTHORS.rst
BeamNG.gym-0.2.dist-info/LICENSE.txt
BeamNG.gym-0.2.dist-info/METADATA
BeamNG.gym-0.2.dist-info/WHEEL
BeamNG.gym-0.2.dist-info/top_level.txt
BeamNG.gym-0.2.dist-info/RECORD
