Metadata-Version: 2.1
Name: BeamNG.gym
Version: 0.2
Summary: BeamNG.gym is a collection of Gymnasium environments that cover various driving tasks simulated in BeamNG.research.
Home-page: https://github.com/BeamNG/BeamNG.gym
Author: BeamNG GmbH
Author-email: tech@beamng.gmbh
License: MIT
Platform: any
Classifier: Development Status :: 4 - Beta
Classifier: Programming Language :: Python
Requires-Python: >=3.8
License-File: LICENSE.txt
License-File: AUTHORS.rst
Requires-Dist: numpy
Requires-Dist: scipy
Requires-Dist: gymnasium
Requires-Dist: shapely
Requires-Dist: beamngpy ==1.27
Requires-Dist: importlib-metadata ; python_version < "3.8"
Provides-Extra: testing
Requires-Dist: pytest ; extra == 'testing'
Requires-Dist: pytest-cov ; extra == 'testing'
